mlacs/__init__.py
mlacs/mlas.py
mlacs/mlminimizer.py
mlacs/otf_mlacs.py
mlacs/version.py
mlacs/calc/__init__.py
mlacs/calc/abinit_manager.py
mlacs/calc/calc_manager.py
mlacs/calc/database_calc.py
mlacs/calc/dlm_calc.py
mlacs/calc/socket.py
mlacs/cli/__init__.py
mlacs/cli/correlation.py
mlacs/cli/main.py
mlacs/cli/plot_error.py
mlacs/cli/plot_neff.py
mlacs/cli/plot_thermo.py
mlacs/cli/plot_weights.py
mlacs/core/__init__.py
mlacs/core/gpinterface.py
mlacs/core/manager.py
mlacs/core/path_atoms.py
mlacs/mlip/__init__.py
mlacs/mlip/_mtp_data.py
mlacs/mlip/ace_descriptor.py
mlacs/mlip/calculator.py
mlacs/mlip/delta_learning.py
mlacs/mlip/descriptor.py
mlacs/mlip/linear_potential.py
mlacs/mlip/mbar_manager.py
mlacs/mlip/mliap_descriptor.py
mlacs/mlip/mlip_manager.py
mlacs/mlip/mtp_model.py
mlacs/mlip/snap_descriptor.py
mlacs/mlip/tensorpotential.py
mlacs/mlip/utilities.py
mlacs/mlip/weighting_policy.py
mlacs/mlip/weights.py
mlacs/properties/__init__.py
mlacs/properties/basic_function.py
mlacs/properties/calc_property.py
mlacs/properties/property_manager.py
mlacs/state/__init__.py
mlacs/state/lammps_state.py
mlacs/state/langevin.py
mlacs/state/mep_ase_state.py
mlacs/state/neb_lammps_state.py
mlacs/state/optimize_ase_state.py
mlacs/state/optimize_lammps_state.py
mlacs/state/pafi_lammps_state.py
mlacs/state/spin_lammps_state.py
mlacs/state/state.py
mlacs/ti/__init__.py
mlacs/ti/liquids.py
mlacs/ti/pressure_scaling.py
mlacs/ti/reversible_scaling.py
mlacs/ti/solids.py
mlacs/ti/thermoint.py
mlacs/ti/thermostate.py
mlacs/utilities/__init__.py
mlacs/utilities/io.py
mlacs/utilities/io_abinit.py
mlacs/utilities/io_lammps.py
mlacs/utilities/io_pandas.py
mlacs/utilities/log.py
mlacs/utilities/miscellanous.py
mlacs/utilities/path_integral.py
mlacs/utilities/pdf.py
mlacs/utilities/plots.py
mlacs/utilities/thermo.py
mlacs/utilities/units.py
tests/__init__.py
tests/conftest.py
tests/context.py
tests/test_cli.py
tests/test_examples.py
tests/integrated_testing/__init__.py
mlacs-1.0.2.dist-info/METADATA
mlacs-1.0.2.dist-info/WHEEL
mlacs-1.0.2.dist-info/entry_points.txt
mlacs-1.0.2.dist-info/top_level.txt
mlacs-1.0.2.dist-info/RECORD
