Metadata-Version: 2.2
Name: mlacs
Version: 1.0.2
Summary: Machine-Learning Assisted Canonical Sampling
Author: Aloïs Castellano
Author-email: alois.castellano@uliege.be
Requires-Dist: numpy>=1.17.0
Requires-Dist: ase>=3.22
Dynamic: author
Dynamic: author-email
Dynamic: description
Dynamic: requires-dist
Dynamic: summary
